sigma/backends/QRadarAQL/QRadarAQL.py
sigma/backends/QRadarAQL/__init__.py
sigma/pipelines/QRadarAQL/QRadarAQL.py
sigma/pipelines/QRadarAQL/QRadarAQL_fields.py
sigma/pipelines/QRadarAQL/QRadarAQL_payload.py
sigma/pipelines/QRadarAQL/__init__.py
pysigma_backend_qradar_aql1-0.1.0.dist-info/LICENSE
pysigma_backend_qradar_aql1-0.1.0.dist-info/METADATA
pysigma_backend_qradar_aql1-0.1.0.dist-info/WHEEL
pysigma_backend_qradar_aql1-0.1.0.dist-info/RECORD
