Metadata-Version: 2.1
Name: pysigma-backend-qradar-aql1
Version: 0.1.0
Summary: pySigma QRadarAQL backend
Home-page: https://github.com/IBM/pySigma-backend-QRadar-AQL
License: MIT
Author: IBM
Author-email: noaakless@gmail.com
Requires-Python: >=3.8,<4.0
Classifier: License :: OSI Approved :: MIT License
Classifier: Programming Language :: Python :: 3
Classifier: Programming Language :: Python :: 3.8
Classifier: Programming Language :: Python :: 3.9
Classifier: Programming Language :: Python :: 3.10
Classifier: Programming Language :: Python :: 3.11
Requires-Dist: pysigma (>=0.9.8,<0.10.0)
Project-URL: Repository, https://github.com/IBM/pySigma-backend-QRadar-AQL
